simulationparsers/__init__.py
simulationparsers/utils/__init__.py
simulationparsers/utils/basic_parser.py
simulationparsers/utils/re_patterns.py
tests/test_utils.py
nomad_parser_plugins_simulation-1.0.2.dist-info/LICENSE
nomad_parser_plugins_simulation-1.0.2.dist-info/METADATA
nomad_parser_plugins_simulation-1.0.2.dist-info/WHEEL
nomad_parser_plugins_simulation-1.0.2.dist-info/top_level.txt
nomad_parser_plugins_simulation-1.0.2.dist-info/RECORD
