Metadata-Version: 2.1
Name: nomad-parser-plugins-simulation
Version: 1.0.2
Summary: Collection of NOMAD parsers for simulation codes.
Author: The NOMAD Authors
License: 
Project-URL: homepage, https://github.com/nomad-coe/simulation-parsers
License-File: LICENSE
Requires-Dist: nomad-lab >=1.3.6
Requires-Dist: nomad-schema-plugin-run >=1.0.1
Provides-Extra: dev
Requires-Dist: mypy ==1.0.1 ; extra == 'dev'
Requires-Dist: pytest <6.0.0,>=5.3.0 ; extra == 'dev'
Requires-Dist: pytest-timeout ==1.4.2 ; extra == 'dev'
Requires-Dist: pytest-cov ==2.7.1 ; extra == 'dev'
Requires-Dist: astroid ==2.11.7 ; extra == 'dev'
Requires-Dist: typing-extensions ==4.4.0 ; extra == 'dev'
Requires-Dist: ruff ==0.1.4 ; extra == 'dev'
